pytorch_ood/__init__.py
pytorch_ood/api.py
pytorch_ood/augment/__init__.py
pytorch_ood/augment/img/__init__.py
pytorch_ood/augment/img/cocopaste.py
pytorch_ood/augment/img/pixmix.py
pytorch_ood/benchmark/__init__.py
pytorch_ood/benchmark/base.py
pytorch_ood/benchmark/img/__init__.py
pytorch_ood/benchmark/img/cifar10.py
pytorch_ood/benchmark/img/cifar100.py
pytorch_ood/benchmark/img/imagenet.py
pytorch_ood/dataset/__init__.py
pytorch_ood/dataset/audio/__init__.py
pytorch_ood/dataset/audio/fsdd.py
pytorch_ood/dataset/img/__init__.py
pytorch_ood/dataset/img/base.py
pytorch_ood/dataset/img/chars74k.py
pytorch_ood/dataset/img/cifar.py
pytorch_ood/dataset/img/fishyscapes.py
pytorch_ood/dataset/img/fooling.py
pytorch_ood/dataset/img/goe.py
pytorch_ood/dataset/img/imagenet.py
pytorch_ood/dataset/img/mnistc.py
pytorch_ood/dataset/img/mvtech.py
pytorch_ood/dataset/img/ninco.py
pytorch_ood/dataset/img/noise.py
pytorch_ood/dataset/img/odin.py
pytorch_ood/dataset/img/openood.py
pytorch_ood/dataset/img/pixmix.py
pytorch_ood/dataset/img/roadanomaly.py
pytorch_ood/dataset/img/smiyc.py
pytorch_ood/dataset/img/streethazards.py
pytorch_ood/dataset/img/sumnist.py
pytorch_ood/dataset/img/textures.py
pytorch_ood/dataset/img/tinyimagenet.py
pytorch_ood/dataset/img/tinyimages.py
pytorch_ood/dataset/ossim/__init__.py
pytorch_ood/dataset/ossim/ossim.py
pytorch_ood/dataset/txt/__init__.py
pytorch_ood/dataset/txt/multi30k.py
pytorch_ood/dataset/txt/newsgroups.py
pytorch_ood/dataset/txt/reuters.py
pytorch_ood/dataset/txt/stop_words.py
pytorch_ood/dataset/txt/wiki.py
pytorch_ood/dataset/txt/wmt16.py
pytorch_ood/detector/__init__.py
pytorch_ood/detector/ash.py
pytorch_ood/detector/dice.py
pytorch_ood/detector/energy.py
pytorch_ood/detector/entropy.py
pytorch_ood/detector/gradnorm.py
pytorch_ood/detector/gram.py
pytorch_ood/detector/klmatching.py
pytorch_ood/detector/knn.py
pytorch_ood/detector/mahalanobis.py
pytorch_ood/detector/maxlogit.py
pytorch_ood/detector/mcd.py
pytorch_ood-0.2.3.dist-info/licenses/LICENSE
pytorch_ood-0.2.3.dist-info/METADATA
pytorch_ood-0.2.3.dist-info/WHEEL
pytorch_ood-0.2.3.dist-info/top_level.txt
pytorch_ood-0.2.3.dist-info/RECORD
