Metadata-Version: 2.4
Name: pytorch-ood
Version: 0.2.3
Summary: A Library for Out-of-Distribution Detection with PyTorch
Home-page: https://github.com/kkirchheim/pytorch-ood
Author: Konstantin Kirchheim
License: Apache 2.0
Project-URL: Bug Tracker, https://github.com/kkirchheim/pytorch-ood/issues
Project-URL: repository, https://github.com/kkirchheim/pytorch-ood
Keywords: OOD,PyTorch,Out-of-Distribution Detection
Classifier: Programming Language :: Python :: 3
Classifier: Operating System :: OS Independent
Requires-Python: >=3.8
License-File: LICENSE
Requires-Dist: torch>=1.7.0
Requires-Dist: torchvision>=0.12.0
Requires-Dist: torchmetrics>=1.0.0
Requires-Dist: scipy>=1.7.0
Requires-Dist: numpy>=1.23.0
Dynamic: license-file
